{"version":1,"resource":"vsls:/plot_ofdm_signal.m","entries":[{"id":"9SwS.m","source":"Workspace Edit","timestamp":null},{"id":"Nsa5.m","timestamp":null},{"id":"OpzK.m","source":"Workspace Edit","timestamp":null},{"id":"45uE.m","timestamp":null},{"id":"sL3w.m","source":"Workspace Edit","timestamp":null},{"id":"KBDy.m","timestamp":null},{"id":"hr34.m","source":"undoRedo.source","timestamp":null},{"id":"vtPB.m","timestamp":null},{"id":"XLt3.m","source":"Workspace Edit","timestamp":null},{"id":"g6CI.m","timestamp":null},{"id":"4Mg4.m","source":"undoRedo.source","timestamp":null},{"id":"X7Wm.m","timestamp":null},{"id":"14tR.m","source":"Workspace Edit","timestamp":null},{"id":"Cxkd.m","timestamp":null}]}